README.md
setup.py
viapi/__init__.py
viapi/fileutils.py
viapi_utils.egg-info/PKG-INFO
viapi_utils.egg-info/SOURCES.txt
viapi_utils.egg-info/dependency_links.txt
viapi_utils.egg-info/top_level.txt